{
    "indicator_name": "2_1b",
    "config": {
        "datasets": [
            "pm_new"
        ],
        "schemas": {
            "region":{
                "schema": "2_1b_region",
                "schema_version": "1.0"
            },
            "county": {
                "schema": "2_1b_county",
                "schema_version": "1.0"
                }
        },
        "transformation_api": "Indicator2_1b",
        "transformation_file": "transform_2_1b",
        "transformation_dir": "app.main.transformation",
        "temporal_identifier": "2019",
        "email_address": "mani.46@osu.edu"
    }
}
